TOPSIS_Shobhit_101903095/__init__.py
TOPSIS_Shobhit_101903095/topsis1.py
TOPSIS_Shobhit_101903095-0.0.1.dist-info/LICENSE.txt
TOPSIS_Shobhit_101903095-0.0.1.dist-info/METADATA
TOPSIS_Shobhit_101903095-0.0.1.dist-info/WHEEL
TOPSIS_Shobhit_101903095-0.0.1.dist-info/top_level.txt
TOPSIS_Shobhit_101903095-0.0.1.dist-info/RECORD
