Metadata-Version: 2.1
Name: TOPSIS-Shobhit-101903095
Version: 0.0.1
Summary: THIS PACKAGE IS TO IMPLEMENT TOPSIS
Author: Shobhit Gupta
Author-email: sgupta3_be19@thapar.edu
License: MIT
Platform: UNKNOWN
Classifier: Development Status :: 3 - Alpha
Classifier: Intended Audience :: Developers
Classifier: Topic :: Software Development :: Build Tools
Classifier: License :: OSI Approved :: MIT License
Classifier: Programming Language :: Python :: 3
Classifier: Programming Language :: Python :: 3.4
Classifier: Programming Language :: Python :: 3.5
Classifier: Programming Language :: Python :: 3.6
License-File: LICENSE.txt
Requires-Dist: pandas
Requires-Dist: numpy
